bytedance_pytest_archer_reporter/__init__.py
bytedance_pytest_archer_reporter-0.0.1.dist-info/METADATA
bytedance_pytest_archer_reporter-0.0.1.dist-info/WHEEL
bytedance_pytest_archer_reporter-0.0.1.dist-info/top_level.txt
bytedance_pytest_archer_reporter-0.0.1.dist-info/RECORD
