Metadata-Version: 2.1
Name: bytedance-pytest-archer-reporter
Version: 0.0.1
Summary: A simple package named bytedance_pytest_archer_reporter
Home-page: https://github.com/artifact/bytedance_pytest_archer_reporter.git
Author: artifact
Author-email: artifact@example.com
License: UNKNOWN
Platform: UNKNOWN
Classifier: Programming Language :: Python :: 3
Classifier: License :: OSI Approved :: MIT License
Classifier: Operating System :: OS Independent
